smime/__init__.py
smime/api.py
smime/block.py
smime/cert.py
smime/encrypt.py
smime/encrypt_test.py
smime/print_util.py
smime/print_util_test.py
smime/pubkey.py
smime/test/__init__.py
smime/test/test_config.py
smime/test/time_utils.py
smime/tests/__init__.py
smime/tests/conftest.py
smime/tests/fixtures.py
smime/tests/test_encrypt.py
smime/tests/test_print_util.py
smime/tools/__init__.py
smime/tools/cert_util.py
smime/tools/cms_util.py
smime_py23-0.1.0b1.dist-info/AUTHORS
smime_py23-0.1.0b1.dist-info/LICENSE
smime_py23-0.1.0b1.dist-info/METADATA
smime_py23-0.1.0b1.dist-info/WHEEL
smime_py23-0.1.0b1.dist-info/top_level.txt
smime_py23-0.1.0b1.dist-info/RECORD
