Metadata-Version: 2.1
Name: smime-py23
Version: 0.1.0b1
Summary: Python S/MIME Toolkit
Home-page: https://github.com/balena/python-smime
Author: G. B. Versiani
Author-email: guibv@yahoo.com
License: Apache License (2.0)
Keywords: smime cryptography email
Platform: all
Classifier: Development Status :: 4 - Beta
Classifier: Operating System :: OS Independent
Classifier: Intended Audience :: Developers
Classifier: License :: OSI Approved :: Apache Software License
Classifier: Programming Language :: Python :: 2.7
Classifier: Programming Language :: Python :: 3
Classifier: Programming Language :: Python :: 3.5
Classifier: Programming Language :: Python :: 3.6
Classifier: Programming Language :: Python :: 3.7
Classifier: Topic :: Software Development :: Libraries
Classifier: Topic :: Communications :: Email
Classifier: Topic :: Security :: Cryptography
Requires-Dist: cryptography
Requires-Dist: asn1crypto
Requires-Dist: six
Provides-Extra: test
Requires-Dist: pytest ; extra == 'test'
Requires-Dist: pytest-flake8 ; extra == 'test'
Requires-Dist: pytest-cov ; extra == 'test'
